powerkube_fork/__init__.py
powerkube_fork-0.2.1.dist-info/LICENSE
powerkube_fork-0.2.1.dist-info/METADATA
powerkube_fork-0.2.1.dist-info/WHEEL
powerkube_fork-0.2.1.dist-info/entry_points.txt
powerkube_fork-0.2.1.dist-info/top_level.txt
powerkube_fork-0.2.1.dist-info/RECORD
