Metadata-Version: 2.1
Name: powerkube-fork
Version: 0.2.1
Summary: A powerline segment to show kubernetes context items, with toggling and alert color functionality
Home-page: https://github.com/d2iq-shadowbq/powerkube-fork
Author: Scott MacGregor
Author-email: smacgregor@d2iq.com
License: Apache 2.0
Download-URL: https://github.com/d2iq-shadowbq/powerkube-fork/tarball/0.2.1
Keywords: kubernetes_py,k8s,powerline,powerkube
Platform: UNKNOWN
Classifier: Programming Language :: Python :: 3
Classifier: Environment :: Console
Classifier: Intended Audience :: Developers
Classifier: License :: OSI Approved :: Apache Software License
Classifier: Topic :: Terminals
Requires-Python: >=3.6
Requires-Dist: kubernetes-py (>=1.10.7.4)
Requires-Dist: powerline-status (>=2.7)
